wagtail_ai/__init__.py
wagtail_ai/apps.py
wagtail_ai/blocks.py
wagtail_ai/context.py
wagtail_ai/forms.py
wagtail_ai/models.py
wagtail_ai/panels.py
wagtail_ai/prompts.py
wagtail_ai/tokens.py
wagtail_ai/types.py
wagtail_ai/views.py
wagtail_ai/wagtail_hooks.py
wagtail_ai/agents/__init__.py
wagtail_ai/agents/base.py
wagtail_ai/agents/basic_prompt.py
wagtail_ai/agents/content_feedback.py
wagtail_ai/agents/suggested_content.py
wagtail_ai/ai/__init__.py
wagtail_ai/ai/base.py
wagtail_ai/ai/echo.py
wagtail_ai/ai/llm.py
wagtail_ai/ai/openai.py
wagtail_ai/locale/ar/LC_MESSAGES/django.mo
wagtail_ai/locale/ar/LC_MESSAGES/django.po
wagtail_ai/locale/ar/LC_MESSAGES/djangojs.mo
wagtail_ai/locale/ar/LC_MESSAGES/djangojs.po
wagtail_ai/locale/be/LC_MESSAGES/django.mo
wagtail_ai/locale/be/LC_MESSAGES/django.po
wagtail_ai/locale/be/LC_MESSAGES/djangojs.mo
wagtail_ai/locale/be/LC_MESSAGES/djangojs.po
wagtail_ai/locale/ca/LC_MESSAGES/django.mo
wagtail_ai/locale/ca/LC_MESSAGES/django.po
wagtail_ai/locale/ca/LC_MESSAGES/djangojs.mo
wagtail_ai/locale/ca/LC_MESSAGES/djangojs.po
wagtail_ai/locale/cs/LC_MESSAGES/django.mo
wagtail_ai/locale/cs/LC_MESSAGES/django.po
wagtail_ai/locale/cs/LC_MESSAGES/djangojs.mo
wagtail_ai/locale/cs/LC_MESSAGES/djangojs.po
wagtail_ai/locale/cy/LC_MESSAGES/django.mo
wagtail_ai/locale/cy/LC_MESSAGES/django.po
wagtail_ai/locale/cy/LC_MESSAGES/djangojs.mo
wagtail_ai/locale/cy/LC_MESSAGES/djangojs.po
wagtail_ai/locale/de/LC_MESSAGES/django.mo
wagtail_ai/locale/de/LC_MESSAGES/django.po
wagtail_ai/locale/de/LC_MESSAGES/djangojs.mo
wagtail_ai/locale/de/LC_MESSAGES/djangojs.po
wagtail_ai/locale/dv/LC_MESSAGES/django.mo
wagtail_ai/locale/dv/LC_MESSAGES/django.po
wagtail_ai/locale/dv/LC_MESSAGES/djangojs.mo
wagtail_ai/locale/dv/LC_MESSAGES/djangojs.po
wagtail_ai/locale/el/LC_MESSAGES/django.mo
wagtail_ai/locale/el/LC_MESSAGES/django.po
wagtail_ai/locale/el/LC_MESSAGES/djangojs.mo
wagtail_ai/locale/el/LC_MESSAGES/djangojs.po
wagtail_ai/locale/es/LC_MESSAGES/django.mo
wagtail_ai-3.0.0.dist-info/licenses/LICENSE
wagtail_ai-3.0.0.dist-info/licenses/LICENSE_LANGCHAIN
wagtail_ai-3.0.0.dist-info/WHEEL
wagtail_ai-3.0.0.dist-info/METADATA
wagtail_ai-3.0.0.dist-info/RECORD
