Metadata-Version: 2.4
Name: wagtail-ai
Version: 3.0.0
Summary: Get a hand writing your content with AI super powers!
Author-email: Tom Usher <tom@tomusher.com>
Requires-Python: >=3.11
Classifier: Development Status :: 3 - Alpha
Classifier: Intended Audience :: Developers
Classifier: License :: OSI Approved :: MIT License
Classifier: Operating System :: OS Independent
Classifier: Programming Language :: Python
Classifier: Programming Language :: Python :: 3
Classifier: Programming Language :: Python :: 3.11
Classifier: Programming Language :: Python :: 3.12
Classifier: Programming Language :: Python :: 3.13
Classifier: Framework :: Django
Classifier: Framework :: Django :: 4.2
Classifier: Framework :: Django :: 5.0
Classifier: Framework :: Wagtail
Classifier: Framework :: Wagtail :: 7
License-File: LICENSE
License-File: LICENSE_LANGCHAIN
Requires-Dist: Django>=4.2
Requires-Dist: Wagtail>=7.1
Requires-Dist: django-ai-core
Requires-Dist: llm>=0.12
Requires-Dist: mkdocs>=1.5.3 ; extra == "docs"
Requires-Dist: mkdocs-material>=9.4.5 ; extra == "docs"
Requires-Dist: mkdocs-awesome-pages-plugin>=2.9.2 ; extra == "docs"
Requires-Dist: beautifulsoup4>=4.11 ; extra == "testing"
Requires-Dist: dj-database-url==2.1.0 ; extra == "testing"
Requires-Dist: pre-commit>=3.6.0 ; extra == "testing"
Requires-Dist: django-types>=0.18.0 ; extra == "testing"
Requires-Dist: pytest>=7.4.2 ; extra == "testing"
Requires-Dist: pytest-django>=4.5.2 ; extra == "testing"
Requires-Dist: pytest-mock>=3.12.0 ; extra == "testing"
Requires-Dist: wagtail-factories>=4.1.0 ; extra == "testing"
Requires-Dist: factory-boy>=3.3.0 ; extra == "testing"
Requires-Dist: coverage>=7.4.0 ; extra == "testing"
Project-URL: Home, https://github.com/wagtail/wagtail-ai
Provides-Extra: docs
Provides-Extra: testing
